jparser
