Metadata-Version: 1.0
Name: jparser
Version: 0.0.17
Summary: A robust parser which can extract title, content, images from html pages
Home-page: UNKNOWN
Author: Sun, Junyi
Author-email: UNKNOWN
License: MIT
Platform: UNKNOWN
